GaoshengQukuaiLianBaogaoQukuaiLianCongLilunZouxiangShijian/README.md
GaoshengQukuaiLianBaogaoQukuaiLianCongLilunZouxiangShijian/__init__.py
GaoshengQukuaiLianBaogaoQukuaiLianCongLilunZouxiangShijian/__main__.py
GaoshengQukuaiLianBaogaoQukuaiLianCongLilunZouxiangShijian/file.epub
GaoshengQukuaiLianBaogaoQukuaiLianCongLilunZouxiangShijian/index.html
GaoshengQukuaiLianBaogaoQukuaiLianCongLilunZouxiangShijian/css/__init__.py
GaoshengQukuaiLianBaogaoQukuaiLianCongLilunZouxiangShijian/css/annotations.css
GaoshengQukuaiLianBaogaoQukuaiLianCongLilunZouxiangShijian/css/main.css
GaoshengQukuaiLianBaogaoQukuaiLianCongLilunZouxiangShijian/css/normalize.css
GaoshengQukuaiLianBaogaoQukuaiLianCongLilunZouxiangShijian/css/popup.css
GaoshengQukuaiLianBaogaoQukuaiLianCongLilunZouxiangShijian/font/__init__.py
GaoshengQukuaiLianBaogaoQukuaiLianCongLilunZouxiangShijian/font/fontello.eot
GaoshengQukuaiLianBaogaoQukuaiLianCongLilunZouxiangShijian/font/fontello.svg
GaoshengQukuaiLianBaogaoQukuaiLianCongLilunZouxiangShijian/font/fontello.ttf
GaoshengQukuaiLianBaogaoQukuaiLianCongLilunZouxiangShijian/font/fontello.woff
GaoshengQukuaiLianBaogaoQukuaiLianCongLilunZouxiangShijian/img/__init__.py
GaoshengQukuaiLianBaogaoQukuaiLianCongLilunZouxiangShijian/img/annotator-glyph-sprite.png
GaoshengQukuaiLianBaogaoQukuaiLianCongLilunZouxiangShijian/img/annotator-icon-sprite.png
GaoshengQukuaiLianBaogaoQukuaiLianCongLilunZouxiangShijian/img/apple-touch-icon.png
GaoshengQukuaiLianBaogaoQukuaiLianCongLilunZouxiangShijian/img/cancelfullscreen.png
GaoshengQukuaiLianBaogaoQukuaiLianCongLilunZouxiangShijian/img/close.png
GaoshengQukuaiLianBaogaoQukuaiLianCongLilunZouxiangShijian/img/fullscreen.png
GaoshengQukuaiLianBaogaoQukuaiLianCongLilunZouxiangShijian/img/loader.gif
GaoshengQukuaiLianBaogaoQukuaiLianCongLilunZouxiangShijian/img/menu-icon.png
GaoshengQukuaiLianBaogaoQukuaiLianCongLilunZouxiangShijian/img/save.png
GaoshengQukuaiLianBaogaoQukuaiLianCongLilunZouxiangShijian/img/saved.png
gaosheng_qukuai_lian_baogao_qukuai_lian_cong_lilun_zouxiang_shijian-2024.3.3.0.dist-info/METADATA
gaosheng_qukuai_lian_baogao_qukuai_lian_cong_lilun_zouxiang_shijian-2024.3.3.0.dist-info/WHEEL
gaosheng_qukuai_lian_baogao_qukuai_lian_cong_lilun_zouxiang_shijian-2024.3.3.0.dist-info/entry_points.txt
gaosheng_qukuai_lian_baogao_qukuai_lian_cong_lilun_zouxiang_shijian-2024.3.3.0.dist-info/top_level.txt
gaosheng_qukuai_lian_baogao_qukuai_lian_cong_lilun_zouxiang_shijian-2024.3.3.0.dist-info/RECORD
